libsumo/__init__.py
libsumo/_libsumo.so
libsumo/libsumo.py
libsumo.libs/libFOX-1-b20b1736.6.so.0.0.59
libsumo.libs/libGLU-ff1477cc.so.1.3.1
libsumo.libs/libXcursor-557eab0f.so.1.0.2
libsumo.libs/libXfixes-e3b7d94c.so.3.1.0
libsumo.libs/libXft-07274ed9.so.2.3.3
libsumo.libs/libXrandr-9f75043e.so.2.2.0
libsumo.libs/libaec-91f0ca0f.so.0.0.8
libsumo.libs/libarmadillo-b35ffa1e.so.12.6.6
libsumo.libs/libarpack-042921fd.so.2.1.0
libsumo.libs/libarrow-90c5e63e.so.2300.0.0
libsumo.libs/libblas-fe34f726.so.3.8.0
libsumo.libs/libbrotlicommon-6ce2a53c.so.1.0.6
libsumo.libs/libbrotlidec-811d1be3.so.1.0.6
libsumo.libs/libbrotlienc-7879b8d6.so.1.0.6
libsumo.libs/libbsd-526a917f.so.0.12.2
libsumo.libs/libbz2-a1e77c99.so.1.0.6
libsumo.libs/libcfitsio-b4c37dff.so.7.3.47
libsumo.libs/libcom_err-730ca923.so.2.1
libsumo.libs/libcrypt-52aca757.so.1.1.0
libsumo.libs/libcrypto-bfee2032.so.1.1.1k
libsumo.libs/libcurl-14a7698c.so.4.5.0
libsumo.libs/libdap-7e467616.so.25.0.1
libsumo.libs/libdapclient-5ca79ace.so.6.1.7
libsumo.libs/libdapserver-e7ab5c47.so.7.6.7
libsumo.libs/libdf-2848fafa.so.0.0.0
libsumo.libs/libfontconfig-dcb2ce6c.so.1.12.0
libsumo.libs/libfreetype-2f3b32b6.so.6.16.1
libsumo.libs/libfreexl-c4cb0770.so.1.1.0
libsumo.libs/libgdal-bed6323b.so.26.0.4
libsumo.libs/libgeos-3-54342c21.7.2.so
libsumo.libs/libgeos_c-e683d5c0.so.1.11.2
libsumo.libs/libgeotiff-cfdb9fd6.so.5.0.0
libsumo.libs/libgfortran-83c28eba.so.5.0.0
libsumo.libs/libgif-5ed6ffef.so.7.0.0
libsumo.libs/libgl2ps-dc8ebcc7.so.1.4.0
libsumo.libs/libgomp-e985bcbb.so.1.0.0
libsumo.libs/libgssapi_krb5-323bbd21.so.2.2
libsumo.libs/libgta-6ed1f83a.so.1.0.0
libsumo.libs/libhdf5-b5e70f84.so.103.1.0
libsumo.libs/libhdf5_hl-0b60eabd.so.100.1.2
libsumo.libs/libidn2-2f4a5893.so.0.3.6
libsumo.libs/libjasper-61dc4fbf.so.4.0.0
libsumo.libs/libjbig-2504a0c3.so.2.1
libsumo.libs/libjpeg-e87d2658.so.62.2.0
libsumo.libs/libjson-c-53e1d64f.so.4.0.0
libsumo.libs/libjupedsim-dc4fe3e9.so
libsumo-1.26.0.dist-info/METADATA
libsumo-1.26.0.dist-info/WHEEL
libsumo-1.26.0.dist-info/RECORD
libsumo-1.26.0.dist-info/licenses/AUTHORS
libsumo-1.26.0.dist-info/licenses/LICENSE
libsumo-1.26.0.dist-info/licenses/NOTICE.md
libsumo-1.26.0.dist-info/sboms/auditwheel.cdx.json
