Metadata-Version: 2.4
Name: libsumo
Version: 1.26.0
Summary: The python version of the libsumo API to communicate with the traffic simulation Eclipse SUMO
Keywords: traffic,simulation,traci
Author-Email: DLR and contributors <sumo@dlr.de>
License-Expression: EPL-2.0 OR GPL-2.0-or-later
Classifier: Development Status :: 5 - Production/Stable
Classifier: Intended Audience :: Developers
Classifier: Intended Audience :: Science/Research
Classifier: Programming Language :: C++
Classifier: Programming Language :: Python
Project-URL: Homepage, https://sumo.dlr.de/
Project-URL: Documentation, https://sumo.dlr.de/docs/Libsumo.html
Project-URL: Repository, https://github.com/eclipse-sumo/sumo
Project-URL: Issues, https://github.com/eclipse-sumo/sumo/issues
Project-URL: Changelog, https://sumo.dlr.de/docs/ChangeLog
Project-URL: Download, https://sumo.dlr.de/download
Requires-Dist: traci>=1.26.0
Requires-Dist: sumo-data>=1.26.0
